fastcmap/__init__.py
fastcmap/base.py
fastcmap/confusematrix.py
fastcmap/map_linedata.py
fastcmap/segmentation.py
fastcmap-0.0.3.dist-info/LICENSE
fastcmap-0.0.3.dist-info/METADATA
fastcmap-0.0.3.dist-info/WHEEL
fastcmap-0.0.3.dist-info/top_level.txt
fastcmap-0.0.3.dist-info/RECORD
